catwalk_client/__init__.py
catwalk_client/client.py
catwalk_client/common/__init__.py
catwalk_client/common/_http_client.py
catwalk_client/common/_session.py
catwalk_client/common/catwalk_http_client.py
catwalk_client/common/constants.py
catwalk_client/common/exception.py
catwalk_client/common/logger.py
catwalk_client/tools/__init__.py
catwalk_client/tools/_case_builder.py
catwalk_client/tools/_case_exporter.py
catwalk_client/tools/_case_exporter_v2.py
catwalk_client-1.1.1.dist-info/METADATA
catwalk_client-1.1.1.dist-info/WHEEL
catwalk_client-1.1.1.dist-info/top_level.txt
catwalk_client-1.1.1.dist-info/RECORD
