Metadata-Version: 2.4
Name: catwalk_client
Version: 1.1.1
Summary: Client for Catwalk
Author-email: Marek Połom <marek.polom@deepsense.ai>, Mateusz Hordyński <mateusz.hordynski@deepsense.ai>, Thor Kikkenborg <thokik@erst.dk>
Classifier: Programming Language :: Python :: 3
Classifier: Operating System :: OS Independent
Requires-Python: >=3.11.0
Requires-Dist: catwalk_common>=0.0.10
